sql2azure/__init__.py
sql2azure/csv_loader.py
sql2azure/json_loader.py
SQL2Azure-1.2.1.dist-info/LICENSE
SQL2Azure-1.2.1.dist-info/METADATA
SQL2Azure-1.2.1.dist-info/WHEEL
SQL2Azure-1.2.1.dist-info/top_level.txt
SQL2Azure-1.2.1.dist-info/RECORD
