Metadata-Version: 2.1
Name: SQL2Azure
Version: 1.2.1
Summary: Load data from an on-prem SQL database to Azure Storage as JSON or CSV.
Home-page: https://github.com/mr-speedster/SQL2Azure
Author: Ajith D
Author-email: ajithd78564@gmail.com
License: MIT
Classifier: Programming Language :: Python :: 3
Classifier: License :: OSI Approved :: MIT License
Classifier: Operating System :: OS Independent
Requires-Python: >=3.6
License-File: LICENSE
Requires-Dist: pyodbc
Requires-Dist: azure-storage-blob
